<?xml version="1.0" encoding="utf-8"?>
<odoo>

	<record id="overtime_manager" model="res.groups">
		<field name="name">Overtime / Manager</field>
		<field name="users"
			eval="[(4, ref('base.user_root')), (4, ref('base.user_admin'))]" />
	</record>
	<record id="overtime_user" model="res.groups">
		<field name="name">Overtime / User</field>
	</record>

	<record model="ir.rule" id="payroll_overtime_view_rule_user">
		<field name="name">Payroll overtime View Rule</field>
		<field name="model_id"
			ref="payroll_overtime.model_hr_payroll_overtime" />
		<field name="groups" eval="[(4, ref('overtime_user'))]" />
		<field name="domain_force">[('created_user', '=', user.id)]</field>
	</record>
	<record model="ir.rule" id="payroll_overtime_view_rule_manager">
		<field name="name">Payroll overtime View Rule</field>
		<field name="model_id"
			ref="payroll_overtime.model_hr_payroll_overtime" />
		<field name="groups" eval="[(4, ref('overtime_manager'))]" />
	</record>
</odoo>
